pymouse-pyhook3/__init__.py
pymouse-pyhook3/base.py
pymouse-pyhook3/java_.py
pymouse-pyhook3/mac.py
pymouse-pyhook3/mir.py
pymouse-pyhook3/wayland.py
pymouse-pyhook3/windows.py
pymouse-pyhook3/x11.py
pymouse_pyhook3/__init__.py
pymouse_pyhook3/base.py
pymouse_pyhook3/java_.py
pymouse_pyhook3/mac.py
pymouse_pyhook3/mir.py
pymouse_pyhook3/wayland.py
pymouse_pyhook3/windows.py
pymouse_pyhook3/x11.py
pymouse_pyhook3-0.1.1.dist-info/METADATA
pymouse_pyhook3-0.1.1.dist-info/WHEEL
pymouse_pyhook3-0.1.1.dist-info/top_level.txt
pymouse_pyhook3-0.1.1.dist-info/RECORD
