Metadata-Version: 2.1
Name: pymouse-pyhook3
Version: 0.1.1
Summary: change "import pyHook" to "import PyHook3 as pyHook"
Home-page: UNKNOWN
Author: Eagle'sBaby
Author-email: 2229066748@qq.com
Maintainer: Eagle'sBaby
Maintainer-email: 2229066748@qq.com
License: Apache Licence 2.0
Keywords: pymouse,PyHook3
Platform: all
Classifier: Programming Language :: Python
Classifier: Programming Language :: Python :: 3
Requires-Python: >=3
